mltools/__init__.py
mltools/log.py
mltools/pandas.py
mltools/data/__init__.py
mltools/data/stability.py
mltools/data/transform.py
mltools/data/features/__init__.py
mltools/data/features/moment.py
mltools/data/features/rfe.py
mltools/data/post/__init__.py
mltools/data/post/blend.py
mltools/data/raw/__init__.py
mltools/data/raw/discretizer.py
mltools/data/raw/encoder.py
mltools/data/raw/interaction.py
mltools/data/raw/model_imputer.py
mltools/data/raw/outliers.py
mltools/data/synthetic/__init__.py
mltools/data/synthetic/random.py
mltools/data/validation/__init__.py
mltools/data/validation/schema.py
hb_mltools-0.1.1.dist-info/METADATA
hb_mltools-0.1.1.dist-info/WHEEL
hb_mltools-0.1.1.dist-info/top_level.txt
hb_mltools-0.1.1.dist-info/RECORD
